nistreamer-0.1.0.dist-info/METADATA
nistreamer-0.1.0.dist-info/WHEEL
nistreamer-0.1.0.dist-info/license_files/LICENSE
nistreamer/card.py
nistreamer/channel.py
nistreamer/proxy/card/ni6535.py
nistreamer/proxy/card/__init__.py
nistreamer/proxy/chan/inverted_do.py
nistreamer/proxy/chan/__init__.py
nistreamer/proxy/__init__.py
nistreamer/streamer.py
nistreamer/utils.py
nistreamer/__init__.py
nistreamer/_nistreamer.pyd
nistreamer-0.1.0.dist-info/RECORD
