Metadata-Version: 2.3
Name: nistreamer
Version: 0.1.0
Classifier: Programming Language :: Python
Classifier: Programming Language :: Rust
Classifier: Intended Audience :: Science/Research
Classifier: Topic :: Scientific/Engineering
Classifier: Topic :: System :: Hardware :: Hardware Drivers
Requires-Dist: numpy
Requires-Dist: plotly
License-File: LICENSE
Summary: An abstraction layer providing a Python API for scripted pulse sequence generation with National Instruments hardware.
Keywords: pulse sequence,experiment control,experiment automation,National Instruments,NI DAQ
Author: NI Pulse Streamer Project and Contributors <https://github.com/NIStreamer>
License: MIT
Requires-Python: >=3.7
Project-URL: Documentation, https://nistreamer.readthedocs.io
Project-URL: GitHub, https://github.com/NIStreamer/nistreamer
Project-URL: Issues, https://github.com/NIStreamer/nistreamer/issues
